pyDHE/DHE_groups.py
pyDHE/__init__.py
pyDHE-1.0.0.dist-info/DESCRIPTION.rst
pyDHE-1.0.0.dist-info/METADATA
pyDHE-1.0.0.dist-info/RECORD
pyDHE-1.0.0.dist-info/WHEEL
pyDHE-1.0.0.dist-info/metadata.json
pyDHE-1.0.0.dist-info/top_level.txt
