Metadata-Version: 2.0
Name: pyDHE
Version: 1.0.0
Summary: a fully python Diffie Hellman implementation
Home-page: https://github.com/deadPix3l/pyDHE
Author: Skyler Curtis
Author-email: skylerr.curtis@gmail.com
License: BSD
Platform: Posix; MacOS X; Windows
Classifier: Development Status :: 4 - Beta
Classifier: License :: OSI Approved :: BSD License
Classifier: License :: Public Domain
Classifier: Intended Audience :: Developers
Classifier: Operating System :: Unix
Classifier: Operating System :: Microsoft :: Windows
Classifier: Operating System :: MacOS :: MacOS X
Classifier: Topic :: Security :: Cryptography
Classifier: Programming Language :: Python :: 2
Classifier: Programming Language :: Python :: 2.4
Classifier: Programming Language :: Python :: 2.5
Classifier: Programming Language :: Python :: 2.6
Classifier: Programming Language :: Python :: 2.7
Classifier: Programming Language :: Python :: 3
Requires-Dist: Crypto
